sql_lib/__init__.py
sql_lib/my_sql_library.py
my_sql_library-0.1.1.dist-info/LICENSE
my_sql_library-0.1.1.dist-info/METADATA
my_sql_library-0.1.1.dist-info/WHEEL
my_sql_library-0.1.1.dist-info/top_level.txt
my_sql_library-0.1.1.dist-info/RECORD
